aliyunsdknis/__init__.py
aliyunsdknis/request/__init__.py
aliyunsdknis/request/v20211216/CreateAndAnalyzeNetworkPathRequest.py
aliyunsdknis/request/v20211216/CreateNetworkPathRequest.py
aliyunsdknis/request/v20211216/CreateNetworkReachableAnalysisRequest.py
aliyunsdknis/request/v20211216/DeleteNetworkPathRequest.py
aliyunsdknis/request/v20211216/DeleteNetworkReachableAnalysisRequest.py
aliyunsdknis/request/v20211216/GetInternetTupleRequest.py
aliyunsdknis/request/v20211216/GetNatTopNRequest.py
aliyunsdknis/request/v20211216/GetNetworkReachableAnalysisRequest.py
aliyunsdknis/request/v20211216/GetNisNetworkMetricsRequest.py
aliyunsdknis/request/v20211216/GetNisNetworkRankingRequest.py
aliyunsdknis/request/v20211216/GetTransitRouterFlowTopNRequest.py
aliyunsdknis/request/v20211216/GetVbrFlowTopNRequest.py
aliyunsdknis/request/v20211216/__init__.py
aliyun_python_sdk_nis-1.0.2.dist-info/LICENSE
aliyun_python_sdk_nis-1.0.2.dist-info/METADATA
aliyun_python_sdk_nis-1.0.2.dist-info/WHEEL
aliyun_python_sdk_nis-1.0.2.dist-info/top_level.txt
aliyun_python_sdk_nis-1.0.2.dist-info/RECORD
